test_run_dir/i2c_TEST/i2c.v
module i2c(
  input        clock,
  input        reset,
  input        io_start,
  input  [6:0] io_addr,
  input  [7:0] io_data,
  input        io_read_write,
  input        io_ack,
  input        io_data_ack,
  output       io_i2c_sda,
  output       io_i2c_scl,
  output       io_ready,
  output       io_stop
);
`ifdef RANDOMIZE_REG_INIT
  reg [31:0] _RAND_0;
  reg [31:0] _RAND_1;
  reg [31:0] _RAND_2;
  reg [31:0] _RAND_3;
  reg [31:0] _RAND_4;
`endif // RANDOMIZE_REG_INIT
  reg [7:0] state; // @[i2c.scala 25:24]
  reg [14:0] count; // @[i2c.scala 26:24]
  reg [6:0] saved_addr; // @[i2c.scala 27:29]
  reg [7:0] saved_data; // @[i2c.scala 28:29]
  reg  i2c_scl_enable; // @[i2c.scala 29:33]
  wire  _GEN_0 = state == 8'h0 | state == 8'h1 | state == 8'h6 ? 1'h0 : 1'h1; // @[i2c.scala 53:87 i2c.scala 54:28 i2c.scala 56:29]
  wire  _GEN_1 = reset ? 1'h0 : _GEN_0; // @[i2c.scala 50:22 i2c.scala 51:24]
  wire  _T_7 = 8'h0 == state; // @[Conditional.scala 37:30]
  wire [2:0] _GEN_2 = io_start ? 3'h1 : 3'h0; // @[i2c.scala 67:39 i2c.scala 68:27 i2c.scala 72:27]
  wire  _T_9 = 8'h1 == state; // @[Conditional.scala 37:30]
  wire  _T_10 = 8'h2 == state; // @[Conditional.scala 37:30]
  wire [6:0] _io_i2c_sda_T = saved_addr >> count; // @[i2c.scala 88:41]
  wire  _T_11 = count == 15'h0; // @[i2c.scala 91:28]
  wire [14:0] _count_T_1 = count - 15'h1; // @[i2c.scala 94:36]
  wire [2:0] _GEN_4 = count == 15'h0 ? 3'h3 : 3'h2; // @[i2c.scala 91:36 i2c.scala 92:27 i2c.scala 95:27]
  wire [14:0] _GEN_5 = count == 15'h0 ? count : _count_T_1; // @[i2c.scala 91:36 i2c.scala 26:24 i2c.scala 94:27]
  wire  _T_12 = 8'h3 == state; // @[Conditional.scala 37:30]
  wire  _GEN_6 = ~io_read_write ? 1'h0 : 1'h1; // @[i2c.scala 101:44 i2c.scala 102:32 i2c.scala 108:32]
  wire [3:0] _GEN_9 = ~io_read_write ? 4'h8 : 4'h7; // @[i2c.scala 101:44 i2c.scala 106:27 i2c.scala 112:27]
  wire  _T_14 = 8'h4 == state; // @[Conditional.scala 37:30]
  wire [7:0] _io_i2c_sda_T_2 = saved_data >> count; // @[i2c.scala 119:41]
  wire [2:0] _GEN_10 = _T_11 ? 3'h5 : 3'h4; // @[i2c.scala 122:36 i2c.scala 123:27 i2c.scala 126:27]
  wire  _T_16 = 8'h5 == state; // @[Conditional.scala 37:30]
  wire  _GEN_15 = _T_16 ? io_data_ack : 1'h1; // @[Conditional.scala 39:67 i2c.scala 132:28]
  wire [2:0] _GEN_17 = _T_16 ? 3'h6 : 3'h0; // @[Conditional.scala 39:67 i2c.scala 135:23]
  wire  _GEN_18 = _T_14 ? _io_i2c_sda_T_2[0] : _GEN_15; // @[Conditional.scala 39:67 i2c.scala 119:28]
  wire [2:0] _GEN_20 = _T_14 ? _GEN_10 : _GEN_17; // @[Conditional.scala 39:67]
  wire [14:0] _GEN_21 = _T_14 ? _GEN_5 : count; // @[Conditional.scala 39:67 i2c.scala 26:24]
  wire  _GEN_22 = _T_12 ? _GEN_6 : _GEN_18; // @[Conditional.scala 39:67]
  wire [2:0] _GEN_24 = _T_12 ? 3'h4 : _GEN_20; // @[Conditional.scala 39:67]
  wire [14:0] _GEN_25 = _T_12 ? {{11'd0}, _GEN_9} : _GEN_21; // @[Conditional.scala 39:67]
  wire  _GEN_26 = _T_10 ? _io_i2c_sda_T[0] : _GEN_22; // @[Conditional.scala 39:67 i2c.scala 88:28]
  wire [2:0] _GEN_28 = _T_10 ? _GEN_4 : _GEN_24; // @[Conditional.scala 39:67]
  wire [14:0] _GEN_29 = _T_10 ? _GEN_5 : _GEN_25; // @[Conditional.scala 39:67]
  wire  _GEN_30 = _T_9 ? 1'h0 : _GEN_26; // @[Conditional.scala 39:67 i2c.scala 78:28]
  wire [2:0] _GEN_35 = _T_9 ? 3'h2 : _GEN_28; // @[Conditional.scala 39:67 i2c.scala 83:23]
  wire  _GEN_37 = _T_7 | _GEN_30; // @[Conditional.scala 40:58 i2c.scala 66:28]
  wire [2:0] _GEN_38 = _T_7 ? _GEN_2 : _GEN_35; // @[Conditional.scala 40:58]
  wire  _GEN_39 = _T_7 ? 1'h0 : _T_9; // @[Conditional.scala 40:58]
  wire [2:0] _GEN_44 = reset ? 3'h0 : _GEN_38; // @[i2c.scala 60:22 i2c.scala 61:15]
  assign io_i2c_sda = reset | _GEN_37; // @[i2c.scala 60:22 i2c.scala 62:20]
  assign io_i2c_scl = ~i2c_scl_enable | ~clock; // @[i2c.scala 48:22]
  assign io_ready = reset ? 1'h0 : _GEN_39; // @[i2c.scala 60:22 i2c.scala 42:14]
  assign io_stop = 1'h0; // @[i2c.scala 60:22 i2c.scala 43:13]
  always @(posedge clock) begin
    if (reset) begin // @[i2c.scala 25:24]
      state <= 8'h0; // @[i2c.scala 25:24]
    end else begin
      state <= {{5'd0}, _GEN_44};
    end
    if (reset) begin // @[i2c.scala 26:24]
      count <= 15'h0; // @[i2c.scala 26:24]
    end else if (!(reset)) begin // @[i2c.scala 60:22]
      if (!(_T_7)) begin // @[Conditional.scala 40:58]
        if (_T_9) begin // @[Conditional.scala 39:67]
          count <= 15'h6; // @[i2c.scala 84:23]
        end else begin
          count <= _GEN_29;
        end
      end
    end
    if (reset) begin // @[i2c.scala 27:29]
      saved_addr <= 7'h0; // @[i2c.scala 27:29]
    end else if (!(reset)) begin // @[i2c.scala 60:22]
      if (!(_T_7)) begin // @[Conditional.scala 40:58]
        if (_T_9) begin // @[Conditional.scala 39:67]
          saved_addr <= io_addr; // @[i2c.scala 79:28]
        end
      end
    end
    if (reset) begin // @[i2c.scala 28:29]
      saved_data <= 8'h0; // @[i2c.scala 28:29]
    end else if (!(reset)) begin // @[i2c.scala 60:22]
      if (!(_T_7)) begin // @[Conditional.scala 40:58]
        if (_T_9) begin // @[Conditional.scala 39:67]
          saved_data <= io_data; // @[i2c.scala 80:28]
        end
      end
    end
    i2c_scl_enable <= reset | _GEN_1; // @[i2c.scala 29:33 i2c.scala 29:33]
  end
// Register and memory initialization
`ifdef RANDOMIZE_GARBAGE_ASSIGN
`define RANDOMIZE
`endif
`ifdef RANDOMIZE_INVALID_ASSIGN
`define RANDOMIZE
`endif
`ifdef RANDOMIZE_REG_INIT
`define RANDOMIZE
`endif
`ifdef RANDOMIZE_MEM_INIT
`define RANDOMIZE
`endif
`ifndef RANDOM
`define RANDOM $random
`endif
`ifdef RANDOMIZE_MEM_INIT
  integer initvar;
`endif
`ifndef SYNTHESIS
`ifdef FIRRTL_BEFORE_INITIAL
`FIRRTL_BEFORE_INITIAL
`endif
initial begin
  `ifdef RANDOMIZE
    `ifdef INIT_RANDOM
      `INIT_RANDOM
    `endif
    `ifndef VERILATOR
      `ifdef RANDOMIZE_DELAY
        #`RANDOMIZE_DELAY begin end
      `else
        #0.002 begin end
      `endif
    `endif
`ifdef RANDOMIZE_REG_INIT
  _RAND_0 = {1{`RANDOM}};
  state = _RAND_0[7:0];
  _RAND_1 = {1{`RANDOM}};
  count = _RAND_1[14:0];
  _RAND_2 = {1{`RANDOM}};
  saved_addr = _RAND_2[6:0];
  _RAND_3 = {1{`RANDOM}};
  saved_data = _RAND_3[7:0];
  _RAND_4 = {1{`RANDOM}};
  i2c_scl_enable = _RAND_4[0:0];
`endif // RANDOMIZE_REG_INIT
  `endif // RANDOMIZE
end // initial
`ifdef FIRRTL_AFTER_INITIAL
`FIRRTL_AFTER_INITIAL
`endif
`endif // SYNTHESIS
endmodule

test_run_dir/i2c_TEST/i2c.vcd
$version Generated by VerilatedVcd $end
$date Mon Mar 21 15:16:02 2022
 $end
$timescale   1ns $end

 $scope module TOP $end
  $var wire  1 K clock $end
  $var wire  1 { io_ack $end
  $var wire  7 c io_addr [6:0] $end
  $var wire  8 k io_data [7:0] $end
  $var wire  1 %! io_data_ack $end
  $var wire  1 5! io_i2c_scl $end
  $var wire  1 -! io_i2c_sda $end
  $var wire  1 s io_read_write $end
  $var wire  1 =! io_ready $end
  $var wire  1 [ io_start $end
  $var wire  1 E! io_stop $end
  $var wire  1 S reset $end
  $scope module i2c $end
   $var wire  1 K clock $end
   $var wire 15 + count [14:0] $end
   $var wire  1 C i2c_scl_enable $end
   $var wire  1 { io_ack $end
   $var wire  7 c io_addr [6:0] $end
   $var wire  8 k io_data [7:0] $end
   $var wire  1 %! io_data_ack $end
   $var wire  1 5! io_i2c_scl $end
   $var wire  1 -! io_i2c_sda $end
   $var wire  1 s io_read_write $end
   $var wire  1 =! io_ready $end
   $var wire  1 [ io_start $end
   $var wire  1 E! io_stop $end
   $var wire  1 S reset $end
   $var wire  7 3 saved_addr [6:0] $end
   $var wire  8 ; saved_data [7:0] $end
   $var wire  8 # state [7:0] $end
  $upscope $end
 $upscope $end
$enddefinitions $end


#0
b00000000 #
b000000000000000 +
b0000000 3
b00000000 ;
0C
0K
1S
0[
b0000000 c
b00000000 k
0s
0{
0%!
1-!
15!
0=!
0E!
#1
1C
1K
05!
#2
0K
0S
1[
b1010101 c
b10101111 k
15!
#3
b00000001 #
0C
1K
0-!
1=!
#4
0K
#5
b00000010 #
b000000000000110 +
b1010101 3
b10101111 ;
1K
1-!
0=!
#6
0K
#7
b000000000000101 +
1C
1K
0-!
05!
#8
0K
15!
#9
b000000000000100 +
1K
1-!
05!
#10
0K
15!
#11
b000000000000011 +
1K
0-!
05!
#12
0K
15!
#13
b000000000000010 +
1K
1-!
05!
#14
0K
15!
#15
b000000000000001 +
1K
0-!
05!
#16
0K
15!
#17
b000000000000000 +
1K
1-!
05!
#18
0K
15!
#19
b00000011 #
1K
0-!
05!
#20
0K
15!
#21
b00000100 #
b000000000001000 +
1K
05!
#22
0K
15!
#23
b000000000000111 +
1K
1-!
05!
#24
0K
15!
#25
b000000000000110 +
1K
0-!
05!
#26
0K
15!
#27
b000000000000101 +
1K
1-!
05!
#28
0K
15!
#29
b000000000000100 +
1K
0-!
05!
#30
0K
15!
#31
b000000000000011 +
1K
1-!
05!
#32
0K
15!
#33
b000000000000010 +
1K
05!
#34
0K
15!
#35
b000000000000001 +
1K
05!
#36
0K
15!
#37
b000000000000000 +
1K
05!
#38
0K
15!
#39
b00000101 #
1K
0-!
05!
#40
0K
15!
#41
b00000110 #
1K
1-!
05!
#42
0K
15!
#43
b00000000 #
0C
1K
#44
0K
#45
b00000001 #
1K
0-!
1=!
#46
0K
#47
b00000010 #
b000000000000110 +
1K
1-!
0=!
#48
0K
#49
b000000000000101 +
1C
1K
0-!
05!
#50
0K
15!
#51
b000000000000100 +
1K
1-!
05!
#52
0K
15!
#53
b000000000000011 +
1K
0-!
05!
#54
0K
15!
#55
b000000000000010 +
1K
1-!
05!
#56
0K
15!
#57
b000000000000001 +
1K
0-!
05!
#58
0K
15!
#59
b000000000000000 +
1K
1-!
05!
#60
0K
15!
#61
b00000011 #
1K
0-!
05!
#62
0K
15!
#63
b00000100 #
b000000000001000 +
1K
05!
#64
0K
15!
#65
b000000000000111 +
1K
1-!
05!
#66
0K
15!
#67
b000000000000110 +
1K
0-!
05!
#68
0K
15!
#69
b000000000000101 +
1K
1-!
05!
#70
0K
15!
#71
b000000000000100 +
1K
0-!
05!
#72
0K
15!
#73
b000000000000011 +
1K
1-!
05!
#74
0K
15!
#75
b000000000000010 +
1K
05!
#76
0K
15!
#77
b000000000000001 +
1K
05!
#78
0K
15!
#79
b000000000000000 +
1K
05!
#80
0K
15!
#81
b00000101 #
1K
0-!
05!
#82
0K
15!
#83
b00000110 #
1K
1-!
05!
#84
0K
15!
#85
b00000000 #
0C
1K
#86
0K
#87
b00000001 #
1K
0-!
1=!
#88
0K
#89
b00000010 #
b000000000000110 +
1K
1-!
0=!
#90
0K
#91
b000000000000101 +
1C
1K
0-!
05!
#92
0K
15!
#93
b000000000000100 +
1K
1-!
05!
#94
0K
15!
#95
b000000000000011 +
1K
0-!
05!
#96
0K
15!
#97
b000000000000010 +
1K
1-!
05!
#98
0K
15!
#99
b000000000000001 +
1K
0-!
05!
#100
0K
15!
#101
b000000000000000 +
1K
1-!
05!
#102
0K
0[
15!
#103
b00000011 #
1K
0-!
05!
#104
0K
15!
#105
b00000100 #
b000000000001000 +
1K
05!
#106
0K
15!
#107
b000000000000111 +
1K
1-!
05!
#108
0K
15!
#109
b000000000000110 +
1K
0-!
05!
#110
0K
15!
#111
b000000000000101 +
1K
1-!
05!
#112
0K
15!
#113
b000000000000100 +
1K
0-!
05!
#114
0K
15!
#115
b000000000000011 +
1K
1-!
05!
#116
0K
15!
#117
b000000000000010 +
1K
05!
#118
0K
15!
#119
b000000000000001 +
1K
05!
#120
0K
15!
#121
b000000000000000 +
1K
05!
#122
0K
15!
#123
b00000101 #
1K
0-!
05!
#124
0K
15!
#125
b00000110 #
1K
1-!
05!
#126
0K
15!
#127
b00000000 #
0C
1K
