test_run_dir/i2c_TEST/i2c_master.v
module i2c_master(
  input        clock,
  input        reset,
  input        io_start,
  input  [6:0] io_addr,
  input  [7:0] io_data,
  input        io_read_write,
  input        io_ack,
  input        io_data_ack,
  output       io_i2c_sda,
  output       io_i2c_scl,
  output       io_ready,
  output       io_stop
);
`ifdef RANDOMIZE_REG_INIT
  reg [31:0] _RAND_0;
  reg [31:0] _RAND_1;
  reg [31:0] _RAND_2;
  reg [31:0] _RAND_3;
  reg [31:0] _RAND_4;
`endif // RANDOMIZE_REG_INIT
  reg [7:0] state; // @[i2c_master.scala 25:24]
  reg [14:0] count; // @[i2c_master.scala 26:24]
  reg [6:0] saved_addr; // @[i2c_master.scala 27:29]
  reg [7:0] saved_data; // @[i2c_master.scala 28:29]
  reg  i2c_scl_enable; // @[i2c_master.scala 29:33]
  wire  _GEN_0 = state == 8'h0 | state == 8'h1 | state == 8'h6 ? 1'h0 : 1'h1; // @[i2c_master.scala 53:87 i2c_master.scala 54:28 i2c_master.scala 56:29]
  wire  _GEN_1 = reset ? 1'h0 : _GEN_0; // @[i2c_master.scala 50:22 i2c_master.scala 51:24]
  wire  _T_7 = 8'h0 == state; // @[Conditional.scala 37:30]
  wire [2:0] _GEN_2 = io_start ? 3'h1 : 3'h0; // @[i2c_master.scala 67:39 i2c_master.scala 68:27 i2c_master.scala 72:27]
  wire  _T_9 = 8'h1 == state; // @[Conditional.scala 37:30]
  wire  _T_10 = 8'h2 == state; // @[Conditional.scala 37:30]
  wire [6:0] _io_i2c_sda_T = saved_addr >> count; // @[i2c_master.scala 88:41]
  wire  _T_11 = count == 15'h0; // @[i2c_master.scala 91:28]
  wire [14:0] _count_T_1 = count - 15'h1; // @[i2c_master.scala 94:36]
  wire [2:0] _GEN_4 = count == 15'h0 ? 3'h3 : 3'h2; // @[i2c_master.scala 91:36 i2c_master.scala 92:27 i2c_master.scala 95:27]
  wire [14:0] _GEN_5 = count == 15'h0 ? count : _count_T_1; // @[i2c_master.scala 91:36 i2c_master.scala 26:24 i2c_master.scala 94:27]
  wire  _T_12 = 8'h3 == state; // @[Conditional.scala 37:30]
  wire  _GEN_6 = ~io_read_write ? 1'h0 : 1'h1; // @[i2c_master.scala 101:44 i2c_master.scala 102:32 i2c_master.scala 108:32]
  wire [3:0] _GEN_9 = ~io_read_write ? 4'h8 : 4'h7; // @[i2c_master.scala 101:44 i2c_master.scala 106:27 i2c_master.scala 112:27]
  wire  _T_14 = 8'h4 == state; // @[Conditional.scala 37:30]
  wire [7:0] _io_i2c_sda_T_2 = saved_data >> count; // @[i2c_master.scala 119:41]
  wire [2:0] _GEN_10 = _T_11 ? 3'h5 : 3'h4; // @[i2c_master.scala 122:36 i2c_master.scala 123:27 i2c_master.scala 126:27]
  wire  _T_16 = 8'h5 == state; // @[Conditional.scala 37:30]
  wire  _GEN_15 = _T_16 ? io_data_ack : 1'h1; // @[Conditional.scala 39:67 i2c_master.scala 132:28]
  wire [2:0] _GEN_17 = _T_16 ? 3'h6 : 3'h0; // @[Conditional.scala 39:67 i2c_master.scala 135:23]
  wire  _GEN_18 = _T_14 ? _io_i2c_sda_T_2[0] : _GEN_15; // @[Conditional.scala 39:67 i2c_master.scala 119:28]
  wire [2:0] _GEN_20 = _T_14 ? _GEN_10 : _GEN_17; // @[Conditional.scala 39:67]
  wire [14:0] _GEN_21 = _T_14 ? _GEN_5 : count; // @[Conditional.scala 39:67 i2c_master.scala 26:24]
  wire  _GEN_22 = _T_12 ? _GEN_6 : _GEN_18; // @[Conditional.scala 39:67]
  wire [2:0] _GEN_24 = _T_12 ? 3'h4 : _GEN_20; // @[Conditional.scala 39:67]
  wire [14:0] _GEN_25 = _T_12 ? {{11'd0}, _GEN_9} : _GEN_21; // @[Conditional.scala 39:67]
  wire  _GEN_26 = _T_10 ? _io_i2c_sda_T[0] : _GEN_22; // @[Conditional.scala 39:67 i2c_master.scala 88:28]
  wire [2:0] _GEN_28 = _T_10 ? _GEN_4 : _GEN_24; // @[Conditional.scala 39:67]
  wire [14:0] _GEN_29 = _T_10 ? _GEN_5 : _GEN_25; // @[Conditional.scala 39:67]
  wire  _GEN_30 = _T_9 ? 1'h0 : _GEN_26; // @[Conditional.scala 39:67 i2c_master.scala 78:28]
  wire [2:0] _GEN_35 = _T_9 ? 3'h2 : _GEN_28; // @[Conditional.scala 39:67 i2c_master.scala 83:23]
  wire  _GEN_37 = _T_7 | _GEN_30; // @[Conditional.scala 40:58 i2c_master.scala 66:28]
  wire [2:0] _GEN_38 = _T_7 ? _GEN_2 : _GEN_35; // @[Conditional.scala 40:58]
  wire  _GEN_39 = _T_7 ? 1'h0 : _T_9; // @[Conditional.scala 40:58]
  wire [2:0] _GEN_44 = reset ? 3'h0 : _GEN_38; // @[i2c_master.scala 60:22 i2c_master.scala 61:15]
  assign io_i2c_sda = reset | _GEN_37; // @[i2c_master.scala 60:22 i2c_master.scala 62:20]
  assign io_i2c_scl = ~i2c_scl_enable | ~clock; // @[i2c_master.scala 48:22]
  assign io_ready = reset ? 1'h0 : _GEN_39; // @[i2c_master.scala 60:22 i2c_master.scala 42:14]
  assign io_stop = 1'h0; // @[i2c_master.scala 60:22 i2c_master.scala 43:13]
  always @(posedge clock) begin
    if (reset) begin // @[i2c_master.scala 25:24]
      state <= 8'h0; // @[i2c_master.scala 25:24]
    end else begin
      state <= {{5'd0}, _GEN_44};
    end
    if (reset) begin // @[i2c_master.scala 26:24]
      count <= 15'h0; // @[i2c_master.scala 26:24]
    end else if (!(reset)) begin // @[i2c_master.scala 60:22]
      if (!(_T_7)) begin // @[Conditional.scala 40:58]
        if (_T_9) begin // @[Conditional.scala 39:67]
          count <= 15'h6; // @[i2c_master.scala 84:23]
        end else begin
          count <= _GEN_29;
        end
      end
    end
    if (reset) begin // @[i2c_master.scala 27:29]
      saved_addr <= 7'h0; // @[i2c_master.scala 27:29]
    end else if (!(reset)) begin // @[i2c_master.scala 60:22]
      if (!(_T_7)) begin // @[Conditional.scala 40:58]
        if (_T_9) begin // @[Conditional.scala 39:67]
          saved_addr <= io_addr; // @[i2c_master.scala 79:28]
        end
      end
    end
    if (reset) begin // @[i2c_master.scala 28:29]
      saved_data <= 8'h0; // @[i2c_master.scala 28:29]
    end else if (!(reset)) begin // @[i2c_master.scala 60:22]
      if (!(_T_7)) begin // @[Conditional.scala 40:58]
        if (_T_9) begin // @[Conditional.scala 39:67]
          saved_data <= io_data; // @[i2c_master.scala 80:28]
        end
      end
    end
    i2c_scl_enable <= reset | _GEN_1; // @[i2c_master.scala 29:33 i2c_master.scala 29:33]
  end
// Register and memory initialization
`ifdef RANDOMIZE_GARBAGE_ASSIGN
`define RANDOMIZE
`endif
`ifdef RANDOMIZE_INVALID_ASSIGN
`define RANDOMIZE
`endif
`ifdef RANDOMIZE_REG_INIT
`define RANDOMIZE
`endif
`ifdef RANDOMIZE_MEM_INIT
`define RANDOMIZE
`endif
`ifndef RANDOM
`define RANDOM $random
`endif
`ifdef RANDOMIZE_MEM_INIT
  integer initvar;
`endif
`ifndef SYNTHESIS
`ifdef FIRRTL_BEFORE_INITIAL
`FIRRTL_BEFORE_INITIAL
`endif
initial begin
  `ifdef RANDOMIZE
    `ifdef INIT_RANDOM
      `INIT_RANDOM
    `endif
    `ifndef VERILATOR
      `ifdef RANDOMIZE_DELAY
        #`RANDOMIZE_DELAY begin end
      `else
        #0.002 begin end
      `endif
    `endif
`ifdef RANDOMIZE_REG_INIT
  _RAND_0 = {1{`RANDOM}};
  state = _RAND_0[7:0];
  _RAND_1 = {1{`RANDOM}};
  count = _RAND_1[14:0];
  _RAND_2 = {1{`RANDOM}};
  saved_addr = _RAND_2[6:0];
  _RAND_3 = {1{`RANDOM}};
  saved_data = _RAND_3[7:0];
  _RAND_4 = {1{`RANDOM}};
  i2c_scl_enable = _RAND_4[0:0];
`endif // RANDOMIZE_REG_INIT
  `endif // RANDOMIZE
end // initial
`ifdef FIRRTL_AFTER_INITIAL
`FIRRTL_AFTER_INITIAL
`endif
`endif // SYNTHESIS
endmodule

test_run_dir/i2c_TEST/i2c_master.vcd
$version Generated by VerilatedVcd $end
$date Sun Mar 27 15:51:44 2022 $end
$timescale 1ps $end

 $scope module TOP $end
  $var wire  1 ( clock $end
  $var wire  1 . io_ack $end
  $var wire  7 + io_addr [6:0] $end
  $var wire  8 , io_data [7:0] $end
  $var wire  1 / io_data_ack $end
  $var wire  1 1 io_i2c_scl $end
  $var wire  1 0 io_i2c_sda $end
  $var wire  1 - io_read_write $end
  $var wire  1 2 io_ready $end
  $var wire  1 * io_start $end
  $var wire  1 3 io_stop $end
  $var wire  1 ) reset $end
  $scope module i2c_master $end
   $var wire  1 ( clock $end
   $var wire 15 $ count [14:0] $end
   $var wire  1 ' i2c_scl_enable $end
   $var wire  1 . io_ack $end
   $var wire  7 + io_addr [6:0] $end
   $var wire  8 , io_data [7:0] $end
   $var wire  1 / io_data_ack $end
   $var wire  1 1 io_i2c_scl $end
   $var wire  1 0 io_i2c_sda $end
   $var wire  1 - io_read_write $end
   $var wire  1 2 io_ready $end
   $var wire  1 * io_start $end
   $var wire  1 3 io_stop $end
   $var wire  1 ) reset $end
   $var wire  7 % saved_addr [6:0] $end
   $var wire  8 & saved_data [7:0] $end
   $var wire  8 # state [7:0] $end
  $upscope $end
 $upscope $end
$enddefinitions $end


#0
b00000000 #
b000000000000000 $
b0000000 %
b00000000 &
0'
0(
1)
0*
b0000000 +
b00000000 ,
0-
0.
0/
10
11
02
03
#1
1'
1(
01
#2
0(
0)
1*
b1111000 +
b10101011 ,
11
#3
b00000001 #
0'
1(
00
12
#4
0(
#5
b00000010 #
b000000000000110 $
b1111000 %
b10101011 &
1(
10
02
#6
0(
#7
b000000000000101 $
1'
1(
01
#8
0(
11
#9
b000000000000100 $
1(
01
#10
0(
11
#11
b000000000000011 $
1(
01
#12
0(
11
#13
b000000000000010 $
1(
00
01
#14
0(
11
#15
b000000000000001 $
1(
01
#16
0(
11
#17
b000000000000000 $
1(
01
#18
0(
11
#19
b00000011 #
1(
01
#20
0(
11
#21
b00000100 #
b000000000001000 $
1(
01
#22
0(
11
#23
b000000000000111 $
1(
10
01
#24
0(
11
#25
b000000000000110 $
1(
00
01
#26
0(
11
#27
b000000000000101 $
1(
10
01
#28
0(
11
#29
b000000000000100 $
1(
00
01
#30
0(
11
#31
b000000000000011 $
1(
10
01
#32
0(
11
#33
b000000000000010 $
1(
00
01
#34
0(
11
#35
b000000000000001 $
1(
10
01
#36
0(
11
#37
b000000000000000 $
1(
01
#38
0(
11
#39
b00000101 #
1(
00
01
#40
0(
11
#41
b00000110 #
1(
10
01
#42
0(
11
#43
b00000000 #
0'
1(
#44
0(
#45
b00000001 #
1(
00
12
#46
0(
#47
b00000010 #
b000000000000110 $
1(
10
02
#48
0(
#49
b000000000000101 $
1'
1(
01
#50
0(
11
#51
b000000000000100 $
1(
01
#52
0(
11
#53
b000000000000011 $
1(
01
#54
0(
11
#55
b000000000000010 $
1(
00
01
#56
0(
11
#57
b000000000000001 $
1(
01
#58
0(
11
#59
b000000000000000 $
1(
01
#60
0(
11
#61
b00000011 #
1(
01
#62
0(
11
#63
b00000100 #
b000000000001000 $
1(
01
#64
0(
11
#65
b000000000000111 $
1(
10
01
#66
0(
11
#67
b000000000000110 $
1(
00
01
#68
0(
11
#69
b000000000000101 $
1(
10
01
#70
0(
11
#71
b000000000000100 $
1(
00
01
#72
0(
11
#73
b000000000000011 $
1(
10
01
#74
0(
11
#75
b000000000000010 $
1(
00
01
#76
0(
11
#77
b000000000000001 $
1(
10
01
#78
0(
11
#79
b000000000000000 $
1(
01
#80
0(
11
#81
b00000101 #
1(
00
01
#82
0(
11
#83
b00000110 #
1(
10
01
#84
0(
11
#85
b00000000 #
0'
1(
#86
0(
#87
b00000001 #
1(
00
12
#88
0(
#89
b00000010 #
b000000000000110 $
1(
10
02
#90
0(
#91
b000000000000101 $
1'
1(
01
#92
0(
11
#93
b000000000000100 $
1(
01
#94
0(
11
#95
b000000000000011 $
1(
01
#96
0(
11
#97
b000000000000010 $
1(
00
01
#98
0(
11
#99
b000000000000001 $
1(
01
#100
0(
11
#101
b000000000000000 $
1(
01
#102
0(
0*
11
#103
b00000011 #
1(
01
#104
0(
11
#105
b00000100 #
b000000000001000 $
1(
01
#106
0(
11
#107
b000000000000111 $
1(
10
01
#108
0(
11
#109
b000000000000110 $
1(
00
01
#110
0(
11
#111
b000000000000101 $
1(
10
01
#112
0(
11
#113
b000000000000100 $
1(
00
01
#114
0(
11
#115
b000000000000011 $
1(
10
01
#116
0(
11
#117
b000000000000010 $
1(
00
01
#118
0(
11
#119
b000000000000001 $
1(
10
01
#120
0(
11
#121
b000000000000000 $
1(
01
#122
0(
11
#123
b00000101 #
1(
00
01
#124
0(
11
#125
b00000110 #
1(
10
01
#126
0(
11
#127
b00000000 #
0'
1(
